{
  "template_data":{
    "category":[
      {
        "name":"lines",
        "subcategory":[
          {
            "name":"basic",
            "item":[
              {
                "description":"Handset Options",
                "type":"loop_line_options",
                "data":{
                  "item":[
                    {
                      "variable":"$ipei",
                      "default_value":"",
                      "description":"Handset IPEI",
                      "type":"input"
                    },
                    {
                      "variable":"$realname",
                      "default_value":"{$displayname.line.{$count}}",
                      "description":"Display Name",
                      "type":"input"
                    },
                    {
                      "type":"break"
                    },
					{
	                  "variable":"$http_pass",
	                  "default_value":"emersive",
	                  "description":"HTTP Password",
	                  "type":"input"
	              	},
                    {
                      "type":"break"
                    },
                    {
                      "type":"break"
                    },
                    {
                      "variable":"$display_text_url",
                      "default_value":"Emersive PBX",
                      "description":"Display text for Idle Screen",
                      "type":"input"
                    }
                  ]
                }
              }
            ]
          },
          {
            "name":"flexable keys",
            "item":[
              {
                "description":"Flexable Keys (1-12)",
                "type":"loop",
                "loop_start":"1",
                "loop_end":"12",
                "data":{
                  "item":[
                    {
                      "variable":"$flexablekey_label",
                      "default_value":"",
                      "description":"Label Name {$count}",
                      "type":"input"
                    },
                    {
                      "variable":"$flexablekey_value",
                      "default_value":"",
                      "description":"Parameter {$count}",
                      "type":"input"
                    },
                    {
                      "variable":"$flexablekey_type",
                      "default_value":"0",
                      "description":"Type {$count}",
                      "type":"list",
                      "data":[
						  {
							"value": "0",
							"text": "None"
						  },
						  {
							"value": "X_PANASONIC_IPTEL_ONETOUCH",
							"text": "One Touch Dial"
						  },
						  {
							"value": "X_PANASONIC_IPTEL_DN",
							"text": "DN"
						  }
                      ]
                    },
                    {
	                  "type":"break"
	                },
	                {
	                  "variable":"$vm_number2",
	                  "default_value":"2999",
	                  "description":"Voicemail Number",
	                  "type":"input"
	                }
                  ]
                }
              }
            ]
          }
        ]
      }
    ]
  }
}
